[
    {
      "id": 1,
      "img": "assets/img/id.png",
      "nombre": "ID Mascotas",
      "precio": 299
    },
    {
      "id": 2,
      "img": "assets/img/props.png",
      "nombre": "Props (10 unidades)",
      "precio": 599
    },
    {
      "id": 3,
      "img": "assets/img/cartel.png",
      "nombre": "Cartel de recibida",
      "precio": 1999
    },
    {
      "id": 4,
      "img": "assets/img/polaroid.png",
      "nombre": "60 Polaroids",
      "precio": 999
    },
    {
      "id": 5,
      "img": "assets/img/cuadro.png",
      "nombre": "Cuadro personalizado 1x0.7m",
      "precio": 4999
    },
    {
      "id": 6,
      "img": "assets/img/calcos.png",
      "nombre": "Pack de 100 calcos",
      "precio": 999
    }
  ]